LICENSE.txt
MANIFEST.in
README.txt
setup.py
pinscher/__init__.py
pinscher/pinscher.py
pinscher.egg-info/PKG-INFO
pinscher.egg-info/SOURCES.txt
pinscher.egg-info/dependency_links.txt
pinscher.egg-info/requires.txt
pinscher.egg-info/top_level.txt
pinscher/test/__init__.py
pinscher/test/test_database.py
pinscher/test/test_vault.py
scripts/pinscher-alfred
scripts/pinscher-cli