Metadata-Version: 1.0
Name: pinscher
Version: 0.1dev
Summary: Core utilities for interacting with pinscher password files
Home-page: http://pinscher.williammayor.co.uk
Author: William Mayor
Author-email: mail@williammayor.co.uk
License: LICENSE.txt
Platform: UNKNOWN
